visumorph/Image.py
visumorph/__init__.py
visumorph/change_hue.py
visumorph/flip.py
visumorph/rotate.py
visumorph/scale.py
visumorph/visumorph.py
visumorph-3.0.1.dist-info/LICENSE
visumorph-3.0.1.dist-info/METADATA
visumorph-3.0.1.dist-info/WHEEL
visumorph-3.0.1.dist-info/RECORD
