Metadata-Version: 2.1
Name: visumorph
Version: 3.0.1
Summary: Package for image manipulations in Python
License: MIT
Author: VisuMorph authors
Requires-Python: >=3.9,<4.0
Classifier: License :: OSI Approved :: MIT License
Classifier: Programming Language :: Python :: 3
Classifier: Programming Language :: Python :: 3.9
Classifier: Programming Language :: Python :: 3.10
Classifier: Programming Language :: Python :: 3.11
Classifier: Programming Language :: Python :: 3.12
Requires-Dist: numpy (>=1.26.3,<2.0.0)
Requires-Dist: pillow (>=10.2.0,<11.0.0)
